CrossappZhongwenWendang/README.md
CrossappZhongwenWendang/__init__.py
CrossappZhongwenWendang/__main__.py
CrossappZhongwenWendang/file.epub
CrossappZhongwenWendang/index.html
CrossappZhongwenWendang/css/__init__.py
CrossappZhongwenWendang/css/annotations.css
CrossappZhongwenWendang/css/main.css
CrossappZhongwenWendang/css/normalize.css
CrossappZhongwenWendang/css/popup.css
CrossappZhongwenWendang/font/__init__.py
CrossappZhongwenWendang/font/fontello.eot
CrossappZhongwenWendang/font/fontello.svg
CrossappZhongwenWendang/font/fontello.ttf
CrossappZhongwenWendang/font/fontello.woff
CrossappZhongwenWendang/img/__init__.py
CrossappZhongwenWendang/img/annotator-glyph-sprite.png
CrossappZhongwenWendang/img/annotator-icon-sprite.png
CrossappZhongwenWendang/img/apple-touch-icon.png
CrossappZhongwenWendang/img/cancelfullscreen.png
CrossappZhongwenWendang/img/close.png
CrossappZhongwenWendang/img/fullscreen.png
CrossappZhongwenWendang/img/loader.gif
CrossappZhongwenWendang/img/menu-icon.png
CrossappZhongwenWendang/img/save.png
CrossappZhongwenWendang/img/saved.png
CrossappZhongwenWendang/img/settings-s.png
CrossappZhongwenWendang/img/settings.png
CrossappZhongwenWendang/img/star.png
CrossappZhongwenWendang/js/__init__.py
CrossappZhongwenWendang/js/epub.js
CrossappZhongwenWendang/js/epub.min.js
CrossappZhongwenWendang/js/epub.min.map
CrossappZhongwenWendang/js/hooks.min.js
CrossappZhongwenWendang/js/hooks.min.map
CrossappZhongwenWendang/js/reader.js
CrossappZhongwenWendang/js/reader.js.map
CrossappZhongwenWendang/js/reader.min.js
CrossappZhongwenWendang/js/reader.min.map
CrossappZhongwenWendang/js/hooks/__init__.py
CrossappZhongwenWendang/js/hooks/extensions/__init__.py
CrossappZhongwenWendang/js/hooks/extensions/highlight.js
CrossappZhongwenWendang/js/libs/__init__.py
CrossappZhongwenWendang/js/libs/jquery.min.js
CrossappZhongwenWendang/js/libs/localforage.min.js
CrossappZhongwenWendang/js/libs/screenfull.js
CrossappZhongwenWendang/js/libs/screenfull.min.js
crossapp_zhongwen_wendang-2024.3.2.0.dist-info/METADATA
crossapp_zhongwen_wendang-2024.3.2.0.dist-info/WHEEL
crossapp_zhongwen_wendang-2024.3.2.0.dist-info/entry_points.txt
crossapp_zhongwen_wendang-2024.3.2.0.dist-info/top_level.txt
crossapp_zhongwen_wendang-2024.3.2.0.dist-info/RECORD
